[
    {
        "client_msg_id": "1236e492-f242-4125-92a0-25a0e87b395d",
        "type": "message",
        "text": "This is a great thread. Employment is a two-way relationship, and like it was well said above, you are the CEO of You before you're anyone's employee! Take care of your path first and the employers you work for will benefit because you will be doing the work you're meant to be doing, whether it's for a month or five years. Loyalty is nice, but again, it goes two ways.",
        "user": "U01FUP6AMEZ",
        "ts": "1611510093.030300",
        "team": "TJE58GTJL",
        "user_team": "TJE58GTJL",
        "source_team": "TJE58GTJL",
        "user_profile": {
            "avatar_hash": "128762c3ea3f",
            "image_72": "https:\/\/avatars.slack-edge.com\/2020-12-01\/1527137254583_128762c3ea3f3d65d19b_72.jpg",
            "first_name": "Joanna",
            "real_name": "Joanna Rutter",
            "display_name": "Joanna Rutter",
            "team": "TJE58GTJL",
            "name": "rutterjoanna",
            "is_restricted": false,
            "is_ultra_restricted": false
        },
        "blocks": [
            {
                "type": "rich_text",
                "block_id": "fESd",
                "elements": [
                    {
                        "type": "rich_text_section",
                        "elements": [
                            {
                                "type": "text",
                                "text": "This is a great thread. Employment is a two-way relationship, and like it was well said above, you are the CEO of You before you're anyone's employee! Take care of your path first and the employers you work for will benefit because you will be doing the work you're meant to be doing, whether it's for a month or five years. Loyalty is nice, but again, it goes two ways."
                            }
                        ]
                    }
                ]
            }
        ],
        "thread_ts": "1610650276.005600",
        "parent_user_id": "U01JP5NAGKT",
        "reactions": [
            {
                "name": "100",
                "users": [
                    "U01JP5NAGKT",
                    "UMX8MPHA6",
                    "U0188DZQPB8"
                ],
                "count": 3
            }
        ]
    }
]