[
    {
        "client_msg_id": "e662f3b2-d816-475c-8816-f7020fd67ba1",
        "type": "message",
        "text": "I was the content Marketing Manager at _<https:\/\/apps.apple.com\/al\/app\/baboon-porosit-ushqim-online\/id1069121718|Baboon>_, a food delivery app, now #1 in Food &amp; Drink in the App Store in Albania, and one of the most successful high-growth startups here. I was in charge of strategy and execution, from tweaking the button copy and doing UXR, to A\/B testing push notifications and interviewing chefs for our blog. So this seems up my alley. What's the workload like?",
        "user": "URL9Z88MR",
        "ts": "1622723842.056100",
        "team": "TJE58GTJL",
        "user_team": "TJE58GTJL",
        "source_team": "TJE58GTJL",
        "user_profile": {
            "avatar_hash": "b378849a08c9",
            "image_72": "https:\/\/avatars.slack-edge.com\/2022-04-19\/3421516666961_b378849a08c9e1d4c33a_72.jpg",
            "first_name": "t1",
            "real_name": "t1",
            "display_name": "t1",
            "team": "TJE58GTJL",
            "name": "delfinahoxha",
            "is_restricted": false,
            "is_ultra_restricted": false
        },
        "attachments": [
            {
                "service_name": "App Store",
                "title": "‎Baboon - Porosit Ushqim Online",
                "title_link": "https:\/\/apps.apple.com\/al\/app\/baboon-porosit-ushqim-online\/id1069121718",
                "text": "‎Baboon ju ofron Shërbim Delivery, Kudo, Kurdo 24\/7. Në kushte të larta sigurie nga +300 Restorante dhe 50 Kuzhina Ndërkombëtare. Restorantet më të famshëm mund ti gjeni në Baboon: KFC, Burger King, Opa, Salt, Sheqer Pikant, PaneVino, Pastaria, Yogurtera, Il Gusto, Goodys, Kungfu Express, Veggies, V…",
                "fallback": "App Store: ‎Baboon - Porosit Ushqim Online",
                "image_url": "https:\/\/is1-ssl.mzstatic.com\/image\/thumb\/Purple113\/v4\/c0\/73\/23\/c0732332-3864-6805-3109-556eb584327a\/AppIcon-0-0-1x_U007emarketing-0-0-0-7-0-0-sRGB-0-0-0-GLES2_U002c0-512MB-85-220-0-0.png\/1200x630wa.png",
                "image_width": 476,
                "image_height": 250,
                "from_url": "https:\/\/apps.apple.com\/al\/app\/baboon-porosit-ushqim-online\/id1069121718",
                "image_bytes": 34512,
                "service_icon": "https:\/\/apps.apple.com\/favicon.ico",
                "id": 1,
                "original_url": "https:\/\/apps.apple.com\/al\/app\/baboon-porosit-ushqim-online\/id1069121718"
            }
        ],
        "blocks": [
            {
                "type": "rich_text",
                "block_id": "o5p\/",
                "elements": [
                    {
                        "type": "rich_text_section",
                        "elements": [
                            {
                                "type": "text",
                                "text": "I was the content Marketing Manager at "
                            },
                            {
                                "type": "link",
                                "url": "https:\/\/apps.apple.com\/al\/app\/baboon-porosit-ushqim-online\/id1069121718",
                                "text": "Baboon",
                                "style": {
                                    "italic": true
                                }
                            },
                            {
                                "type": "text",
                                "text": ", a food delivery app, now #1 in Food & Drink in the App Store in Albania, and one of the most successful high-growth startups here. I was in charge of strategy and execution, from tweaking the button copy and doing UXR, to A\/B testing push notifications and interviewing chefs for our blog. So this seems up my alley. What's the workload like?"
                            }
                        ]
                    }
                ]
            }
        ],
        "thread_ts": "1622695905.056000",
        "parent_user_id": "U01CVQ02E5S"
    },
    {
        "client_msg_id": "b44faef4-c7b8-481b-a8af-780ce55bbbe6",
        "type": "message",
        "text": "happy birthday to <@UP6K3LYQ7>!!!",
        "user": "UKAK6J1NY",
        "ts": "1622725773.056600",
        "team": "TJE58GTJL",
        "user_team": "TJE58GTJL",
        "source_team": "TJE58GTJL",
        "user_profile": {
            "avatar_hash": "g97d298175c3",
            "image_72": "https:\/\/secure.gravatar.com\/avatar\/1797d298175c37a06606a2ac30e258e2.jpg?s=72&d=https%3A%2F%2Fa.slack-edge.com%2Fdf10d%2Fimg%2Favatars%2Fava_0016-72.png",
            "first_name": "Shayna",
            "real_name": "Shayna Hodkin",
            "display_name": "shayna (she\/her)",
            "team": "TJE58GTJL",
            "name": "slhodkin",
            "is_restricted": false,
            "is_ultra_restricted": false
        },
        "blocks": [
            {
                "type": "rich_text",
                "block_id": "2KTr",
                "elements": [
                    {
                        "type": "rich_text_section",
                        "elements": [
                            {
                                "type": "text",
                                "text": "happy birthday to "
                            },
                            {
                                "type": "user",
                                "user_id": "UP6K3LYQ7"
                            },
                            {
                                "type": "text",
                                "text": "!!!"
                            }
                        ]
                    }
                ]
            }
        ],
        "thread_ts": "1622725773.056600",
        "reply_count": 1,
        "reply_users_count": 1,
        "latest_reply": "1623060412.062600",
        "reply_users": [
            "UP6K3LYQ7"
        ],
        "replies": [
            {
                "user": "UP6K3LYQ7",
                "ts": "1623060412.062600"
            }
        ],
        "is_locked": false,
        "subscribed": false,
        "reactions": [
            {
                "name": "birthday",
                "users": [
                    "UUVS8PURK",
                    "U01AHL8AGBB",
                    "U01GWU4JWE4",
                    "U012GHRAHDK",
                    "UUVRK10QG",
                    "U022KM2GZ9T",
                    "UJE5LQ2JC",
                    "UPH4SCGTH",
                    "UJG9WTEKG",
                    "UP6K3LYQ7"
                ],
                "count": 10
            }
        ]
    },
    {
        "client_msg_id": "3a68700d-c6b8-4639-93f5-837c60e94cc9",
        "type": "message",
        "text": "I'm super into veganism x tech if that's interesting!!",
        "user": "UKAK6J1NY",
        "ts": "1622725899.056800",
        "team": "TJE58GTJL",
        "user_team": "TJE58GTJL",
        "source_team": "TJE58GTJL",
        "user_profile": {
            "avatar_hash": "g97d298175c3",
            "image_72": "https:\/\/secure.gravatar.com\/avatar\/1797d298175c37a06606a2ac30e258e2.jpg?s=72&d=https%3A%2F%2Fa.slack-edge.com%2Fdf10d%2Fimg%2Favatars%2Fava_0016-72.png",
            "first_name": "Shayna",
            "real_name": "Shayna Hodkin",
            "display_name": "shayna (she\/her)",
            "team": "TJE58GTJL",
            "name": "slhodkin",
            "is_restricted": false,
            "is_ultra_restricted": false
        },
        "blocks": [
            {
                "type": "rich_text",
                "block_id": "9Fa0M",
                "elements": [
                    {
                        "type": "rich_text_section",
                        "elements": [
                            {
                                "type": "text",
                                "text": "I'm super into veganism x tech if that's interesting!!"
                            }
                        ]
                    }
                ]
            }
        ],
        "thread_ts": "1622695905.056000",
        "parent_user_id": "U01CVQ02E5S"
    },
    {
        "client_msg_id": "acb175af-06f7-4b34-aeae-70cfe35ed6e4",
        "type": "message",
        "text": "Anyone here uses Grammarly add-on on Chrome?\n\nI'd like to know your experiences with regarding speed when working with free version vs the paid version.\n\nI feel like the free version slows down my PC a lot",
        "user": "U0207Q19V0U",
        "ts": "1622771649.059100",
        "team": "TJE58GTJL",
        "user_team": "TJE58GTJL",
        "source_team": "TJE58GTJL",
        "user_profile": {
            "avatar_hash": "bb66b0c0e7eb",
            "image_72": "https:\/\/avatars.slack-edge.com\/2021-04-26\/2002270314323_bb66b0c0e7eb29a9755a_72.jpg",
            "first_name": "",
            "real_name": "Navin Israni",
            "display_name": "Navin Israni",
            "team": "TJE58GTJL",
            "name": "thecreativemastermind",
            "is_restricted": false,
            "is_ultra_restricted": false
        },
        "blocks": [
            {
                "type": "rich_text",
                "block_id": "ouuWd",
                "elements": [
                    {
                        "type": "rich_text_section",
                        "elements": [
                            {
                                "type": "text",
                                "text": "Anyone here uses Grammarly add-on on Chrome?\n\nI'd like to know your experiences with regarding speed when working with free version vs the paid version.\n\nI feel like the free version slows down my PC a lot"
                            }
                        ]
                    }
                ]
            }
        ],
        "thread_ts": "1622771649.059100",
        "reply_count": 7,
        "reply_users_count": 7,
        "latest_reply": "1624107355.100500",
        "reply_users": [
            "U012GHRAHDK",
            "U02280S1Q8P",
            "U01J3L8CJRL",
            "UV5V2P0VB",
            "U01KH3P18RZ",
            "UUY2AL9PG",
            "U01G5ED8K0V"
        ],
        "replies": [
            {
                "user": "U012GHRAHDK",
                "ts": "1622773697.059200"
            },
            {
                "user": "U02280S1Q8P",
                "ts": "1622796141.059600"
            },
            {
                "user": "U01J3L8CJRL",
                "ts": "1622798289.059800"
            },
            {
                "user": "UV5V2P0VB",
                "ts": "1622817424.061100"
            },
            {
                "user": "U01KH3P18RZ",
                "ts": "1622826168.061300"
            },
            {
                "user": "UUY2AL9PG",
                "ts": "1622925420.062000"
            },
            {
                "user": "U01G5ED8K0V",
                "ts": "1624107355.100500"
            }
        ],
        "is_locked": false,
        "subscribed": false
    },
    {
        "client_msg_id": "b67b21dc-0e83-49d8-b3f8-2d972eff8039",
        "type": "message",
        "text": "I found no difference in speed - used it for a good 3 months.",
        "user": "U012GHRAHDK",
        "ts": "1622773697.059200",
        "team": "TJE58GTJL",
        "user_team": "TJE58GTJL",
        "source_team": "TJE58GTJL",
        "user_profile": {
            "avatar_hash": "8ba0c4534568",
            "image_72": "https:\/\/avatars.slack-edge.com\/2022-04-12\/3401585222352_8ba0c45345680ce088ab_72.jpg",
            "first_name": "Deb",
            "real_name": "Deb Mukherjee",
            "display_name": "Deb Mukherjee",
            "team": "TJE58GTJL",
            "name": "debdut94",
            "is_restricted": false,
            "is_ultra_restricted": false
        },
        "blocks": [
            {
                "type": "rich_text",
                "block_id": "pYkf",
                "elements": [
                    {
                        "type": "rich_text_section",
                        "elements": [
                            {
                                "type": "text",
                                "text": "I found no difference in speed - used it for a good 3 months."
                            }
                        ]
                    }
                ]
            }
        ],
        "thread_ts": "1622771649.059100",
        "parent_user_id": "U0207Q19V0U"
    }
]