[
    {
        "client_msg_id": "89c4d3b7-aecc-4792-901e-d87f9851f2cd",
        "type": "message",
        "text": "Hi!",
        "user": "U01941ZDK5K",
        "ts": "1598021262.043400",
        "team": "TJE58GTJL",
        "user_team": "TJE58GTJL",
        "source_team": "TJE58GTJL",
        "user_profile": {
            "avatar_hash": "8de95fbdf470",
            "image_72": "https:\/\/avatars.slack-edge.com\/2020-08-20\/1313601248019_8de95fbdf470edad1aa5_72.jpg",
            "first_name": "Vicki",
            "real_name": "Vicki Thomas",
            "display_name": "Vicki Thomas",
            "team": "TJE58GTJL",
            "name": "vickith",
            "is_restricted": false,
            "is_ultra_restricted": false
        },
        "blocks": [
            {
                "type": "rich_text",
                "block_id": "=Yp",
                "elements": [
                    {
                        "type": "rich_text_section",
                        "elements": [
                            {
                                "type": "text",
                                "text": "Hi!"
                            }
                        ]
                    }
                ]
            }
        ],
        "thread_ts": "1597942797.023900",
        "parent_user_id": "U01941ZDK5K"
    },
    {
        "client_msg_id": "325135f7-1321-4091-807c-27c49713aa0a",
        "type": "message",
        "text": "oh hey <@U017S2P8Z5L>",
        "user": "UJESWE5MJ",
        "ts": "1598024731.043900",
        "team": "TJE58GTJL",
        "user_team": "TJE58GTJL",
        "source_team": "TJE58GTJL",
        "user_profile": {
            "avatar_hash": "082356f2e2cc",
            "image_72": "https:\/\/avatars.slack-edge.com\/2019-05-06\/629642688118_082356f2e2cc41ed3fac_72.jpg",
            "first_name": "Deanna",
            "real_name": "Deanna Cioppa",
            "display_name": "Deanna Cioppa",
            "team": "TJE58GTJL",
            "name": "deanna.cioppa",
            "is_restricted": false,
            "is_ultra_restricted": false
        },
        "blocks": [
            {
                "type": "rich_text",
                "block_id": "jaQ",
                "elements": [
                    {
                        "type": "rich_text_section",
                        "elements": [
                            {
                                "type": "text",
                                "text": "oh hey "
                            },
                            {
                                "type": "user",
                                "user_id": "U017S2P8Z5L"
                            }
                        ]
                    }
                ]
            }
        ],
        "thread_ts": "1596134125.204800",
        "parent_user_id": "U017S2P8Z5L"
    },
    {
        "client_msg_id": "c5a6af0a-af97-49af-b11e-bb23f62f66ee",
        "type": "message",
        "text": "welcome <@U018BH9FT3L>!",
        "user": "UJG9WTEKG",
        "ts": "1598025269.044100",
        "team": "TJE58GTJL",
        "user_team": "TJE58GTJL",
        "source_team": "TJE58GTJL",
        "user_profile": {
            "avatar_hash": "gc25b94e6ebf",
            "image_72": "https:\/\/secure.gravatar.com\/avatar\/eec25b94e6ebf55f0b7933372344cd09.jpg?s=72&d=https%3A%2F%2Fa.slack-edge.com%2Fdf10d%2Fimg%2Favatars%2Fava_0001-72.png",
            "first_name": "Jimmy",
            "real_name": "Jimmy Daly",
            "display_name": "",
            "team": "TJE58GTJL",
            "name": "runjimdaly",
            "is_restricted": false,
            "is_ultra_restricted": false
        },
        "blocks": [
            {
                "type": "rich_text",
                "block_id": "EnTdB",
                "elements": [
                    {
                        "type": "rich_text_section",
                        "elements": [
                            {
                                "type": "text",
                                "text": "welcome "
                            },
                            {
                                "type": "user",
                                "user_id": "U018BH9FT3L"
                            },
                            {
                                "type": "text",
                                "text": "!"
                            }
                        ]
                    }
                ]
            }
        ],
        "thread_ts": "1597944226.028000",
        "parent_user_id": "U018ZNMCC3C"
    },
    {
        "client_msg_id": "d94392a4-7888-4bd9-855a-445f94d4f2e0",
        "type": "message",
        "text": "welcome aboard <@U01941ZDK5K>!",
        "user": "UJG9WTEKG",
        "ts": "1598025299.044300",
        "team": "TJE58GTJL",
        "user_team": "TJE58GTJL",
        "source_team": "TJE58GTJL",
        "user_profile": {
            "avatar_hash": "gc25b94e6ebf",
            "image_72": "https:\/\/secure.gravatar.com\/avatar\/eec25b94e6ebf55f0b7933372344cd09.jpg?s=72&d=https%3A%2F%2Fa.slack-edge.com%2Fdf10d%2Fimg%2Favatars%2Fava_0001-72.png",
            "first_name": "Jimmy",
            "real_name": "Jimmy Daly",
            "display_name": "",
            "team": "TJE58GTJL",
            "name": "runjimdaly",
            "is_restricted": false,
            "is_ultra_restricted": false
        },
        "blocks": [
            {
                "type": "rich_text",
                "block_id": "it5a8",
                "elements": [
                    {
                        "type": "rich_text_section",
                        "elements": [
                            {
                                "type": "text",
                                "text": "welcome aboard "
                            },
                            {
                                "type": "user",
                                "user_id": "U01941ZDK5K"
                            },
                            {
                                "type": "text",
                                "text": "!"
                            }
                        ]
                    }
                ]
            }
        ],
        "thread_ts": "1597942797.023900",
        "parent_user_id": "U01941ZDK5K"
    },
    {
        "client_msg_id": "19dcae85-eca7-4c51-a623-3959192de24f",
        "type": "message",
        "text": "when i was 18, i visited ottawa in january and forgot to bring a jacket",
        "user": "UJG9WTEKG",
        "ts": "1598025316.044500",
        "team": "TJE58GTJL",
        "user_team": "TJE58GTJL",
        "source_team": "TJE58GTJL",
        "user_profile": {
            "avatar_hash": "gc25b94e6ebf",
            "image_72": "https:\/\/secure.gravatar.com\/avatar\/eec25b94e6ebf55f0b7933372344cd09.jpg?s=72&d=https%3A%2F%2Fa.slack-edge.com%2Fdf10d%2Fimg%2Favatars%2Fava_0001-72.png",
            "first_name": "Jimmy",
            "real_name": "Jimmy Daly",
            "display_name": "",
            "team": "TJE58GTJL",
            "name": "runjimdaly",
            "is_restricted": false,
            "is_ultra_restricted": false
        },
        "blocks": [
            {
                "type": "rich_text",
                "block_id": "=vt7u",
                "elements": [
                    {
                        "type": "rich_text_section",
                        "elements": [
                            {
                                "type": "text",
                                "text": "when i was 18, i visited ottawa in january and forgot to bring a jacket"
                            }
                        ]
                    }
                ]
            }
        ],
        "thread_ts": "1597942797.023900",
        "parent_user_id": "U01941ZDK5K"
    },
    {
        "client_msg_id": "9c5ebd33-b408-483e-87e1-2d217cf1c827",
        "type": "message",
        "text": "that was a really bad mistake",
        "user": "UJG9WTEKG",
        "ts": "1598025320.044700",
        "team": "TJE58GTJL",
        "user_team": "TJE58GTJL",
        "source_team": "TJE58GTJL",
        "user_profile": {
            "avatar_hash": "gc25b94e6ebf",
            "image_72": "https:\/\/secure.gravatar.com\/avatar\/eec25b94e6ebf55f0b7933372344cd09.jpg?s=72&d=https%3A%2F%2Fa.slack-edge.com%2Fdf10d%2Fimg%2Favatars%2Fava_0001-72.png",
            "first_name": "Jimmy",
            "real_name": "Jimmy Daly",
            "display_name": "",
            "team": "TJE58GTJL",
            "name": "runjimdaly",
            "is_restricted": false,
            "is_ultra_restricted": false
        },
        "blocks": [
            {
                "type": "rich_text",
                "block_id": "LUY",
                "elements": [
                    {
                        "type": "rich_text_section",
                        "elements": [
                            {
                                "type": "text",
                                "text": "that was a really bad mistake"
                            }
                        ]
                    }
                ]
            }
        ],
        "thread_ts": "1597942797.023900",
        "parent_user_id": "U01941ZDK5K",
        "reactions": [
            {
                "name": "joy",
                "users": [
                    "U010CH02CMP",
                    "U010UHR7PED",
                    "UUVRK10QG"
                ],
                "count": 3
            },
            {
                "name": "snowman",
                "users": [
                    "U010CH02CMP"
                ],
                "count": 1
            }
        ]
    },
    {
        "client_msg_id": "2b06a923-5a4d-4f11-bb40-20a9dc393dee",
        "type": "message",
        "text": "welcome aboard <@U0192P23T51>!",
        "user": "UJG9WTEKG",
        "ts": "1598025347.044900",
        "team": "TJE58GTJL",
        "user_team": "TJE58GTJL",
        "source_team": "TJE58GTJL",
        "user_profile": {
            "avatar_hash": "gc25b94e6ebf",
            "image_72": "https:\/\/secure.gravatar.com\/avatar\/eec25b94e6ebf55f0b7933372344cd09.jpg?s=72&d=https%3A%2F%2Fa.slack-edge.com%2Fdf10d%2Fimg%2Favatars%2Fava_0001-72.png",
            "first_name": "Jimmy",
            "real_name": "Jimmy Daly",
            "display_name": "",
            "team": "TJE58GTJL",
            "name": "runjimdaly",
            "is_restricted": false,
            "is_ultra_restricted": false
        },
        "blocks": [
            {
                "type": "rich_text",
                "block_id": "ePM4l",
                "elements": [
                    {
                        "type": "rich_text_section",
                        "elements": [
                            {
                                "type": "text",
                                "text": "welcome aboard "
                            },
                            {
                                "type": "user",
                                "user_id": "U0192P23T51"
                            },
                            {
                                "type": "text",
                                "text": "!"
                            }
                        ]
                    }
                ]
            }
        ],
        "thread_ts": "1597910064.018800",
        "parent_user_id": "U0192P23T51"
    },
    {
        "client_msg_id": "e39e267c-e964-4945-9f80-ecd1d8479d52",
        "type": "message",
        "text": "Welcome onboard <@U018ZNMCC3C> :smiley:",
        "user": "U01704F04QH",
        "ts": "1598046263.049400",
        "team": "TJE58GTJL",
        "user_team": "TJE58GTJL",
        "source_team": "TJE58GTJL",
        "user_profile": {
            "avatar_hash": "c4babd35d9f8",
            "image_72": "https:\/\/avatars.slack-edge.com\/2020-09-04\/1343175645235_c4babd35d9f8360f26e8_72.jpg",
            "first_name": "Stella",
            "real_name": "Stella Inabo",
            "display_name": "Stella Inabo",
            "team": "TJE58GTJL",
            "name": "stellainabo",
            "is_restricted": false,
            "is_ultra_restricted": false
        },
        "blocks": [
            {
                "type": "rich_text",
                "block_id": "cKpi",
                "elements": [
                    {
                        "type": "rich_text_section",
                        "elements": [
                            {
                                "type": "text",
                                "text": "Welcome onboard "
                            },
                            {
                                "type": "user",
                                "user_id": "U018ZNMCC3C"
                            },
                            {
                                "type": "text",
                                "text": " "
                            },
                            {
                                "type": "emoji",
                                "name": "smiley"
                            }
                        ]
                    }
                ]
            }
        ],
        "thread_ts": "1597944226.028000",
        "parent_user_id": "U018ZNMCC3C",
        "reactions": [
            {
                "name": "raised_hands",
                "users": [
                    "U018ZNMCC3C",
                    "UUVRK10QG"
                ],
                "count": 2
            }
        ]
    },
    {
        "client_msg_id": "7cc9b524-bb6f-4177-b814-a6ae0b6b5155",
        "type": "message",
        "text": "Hey <@U0192P23T51> Nice to meet you!",
        "user": "U01704F04QH",
        "ts": "1598046408.049700",
        "team": "TJE58GTJL",
        "user_team": "TJE58GTJL",
        "source_team": "TJE58GTJL",
        "user_profile": {
            "avatar_hash": "c4babd35d9f8",
            "image_72": "https:\/\/avatars.slack-edge.com\/2020-09-04\/1343175645235_c4babd35d9f8360f26e8_72.jpg",
            "first_name": "Stella",
            "real_name": "Stella Inabo",
            "display_name": "Stella Inabo",
            "team": "TJE58GTJL",
            "name": "stellainabo",
            "is_restricted": false,
            "is_ultra_restricted": false
        },
        "blocks": [
            {
                "type": "rich_text",
                "block_id": "nJW4",
                "elements": [
                    {
                        "type": "rich_text_section",
                        "elements": [
                            {
                                "type": "text",
                                "text": "Hey "
                            },
                            {
                                "type": "user",
                                "user_id": "U0192P23T51"
                            },
                            {
                                "type": "text",
                                "text": " Nice to meet you!"
                            }
                        ]
                    }
                ]
            }
        ],
        "thread_ts": "1597910064.018800",
        "parent_user_id": "U0192P23T51"
    },
    {
        "client_msg_id": "bbeee973-557f-4fc2-b2d3-ae47353e1bcc",
        "type": "message",
        "text": "Hey <@U018YLTQJDU> welcome! I'm also a B2B writer:grinning:. It's great to meet someone in my niche.",
        "user": "U01704F04QH",
        "ts": "1598046498.050000",
        "team": "TJE58GTJL",
        "user_team": "TJE58GTJL",
        "source_team": "TJE58GTJL",
        "user_profile": {
            "avatar_hash": "c4babd35d9f8",
            "image_72": "https:\/\/avatars.slack-edge.com\/2020-09-04\/1343175645235_c4babd35d9f8360f26e8_72.jpg",
            "first_name": "Stella",
            "real_name": "Stella Inabo",
            "display_name": "Stella Inabo",
            "team": "TJE58GTJL",
            "name": "stellainabo",
            "is_restricted": false,
            "is_ultra_restricted": false
        },
        "blocks": [
            {
                "type": "rich_text",
                "block_id": "dy1mo",
                "elements": [
                    {
                        "type": "rich_text_section",
                        "elements": [
                            {
                                "type": "text",
                                "text": "Hey "
                            },
                            {
                                "type": "user",
                                "user_id": "U018YLTQJDU"
                            },
                            {
                                "type": "text",
                                "text": " welcome! I'm also a B2B writer"
                            },
                            {
                                "type": "emoji",
                                "name": "grinning"
                            },
                            {
                                "type": "text",
                                "text": ". It's great to meet someone in my niche."
                            }
                        ]
                    }
                ]
            }
        ],
        "thread_ts": "1597909264.016400",
        "parent_user_id": "U018YLTQJDU"
    },
    {
        "client_msg_id": "0df9f1da-4f0a-4c46-a898-4a9404ae5901",
        "type": "message",
        "text": "Hey <@U019V86UAJU>! Nice to meet you:smile:",
        "user": "U01704F04QH",
        "ts": "1598046552.050300",
        "team": "TJE58GTJL",
        "user_team": "TJE58GTJL",
        "source_team": "TJE58GTJL",
        "user_profile": {
            "avatar_hash": "c4babd35d9f8",
            "image_72": "https:\/\/avatars.slack-edge.com\/2020-09-04\/1343175645235_c4babd35d9f8360f26e8_72.jpg",
            "first_name": "Stella",
            "real_name": "Stella Inabo",
            "display_name": "Stella Inabo",
            "team": "TJE58GTJL",
            "name": "stellainabo",
            "is_restricted": false,
            "is_ultra_restricted": false
        },
        "blocks": [
            {
                "type": "rich_text",
                "block_id": "Z8W",
                "elements": [
                    {
                        "type": "rich_text_section",
                        "elements": [
                            {
                                "type": "text",
                                "text": "Hey "
                            },
                            {
                                "type": "user",
                                "user_id": "U019V86UAJU"
                            },
                            {
                                "type": "text",
                                "text": "! Nice to meet you"
                            },
                            {
                                "type": "emoji",
                                "name": "smile"
                            }
                        ]
                    }
                ]
            }
        ],
        "thread_ts": "1597890639.011900",
        "parent_user_id": "U019V86UAJU"
    },
    {
        "client_msg_id": "e6ae87a9-f6f4-4c47-b2cb-e57c6fa7dcb7",
        "type": "message",
        "text": "Hey <@U0195CX543U> ! Nice to meet you:grin:",
        "user": "U01704F04QH",
        "ts": "1598046630.050700",
        "team": "TJE58GTJL",
        "user_team": "TJE58GTJL",
        "source_team": "TJE58GTJL",
        "user_profile": {
            "avatar_hash": "c4babd35d9f8",
            "image_72": "https:\/\/avatars.slack-edge.com\/2020-09-04\/1343175645235_c4babd35d9f8360f26e8_72.jpg",
            "first_name": "Stella",
            "real_name": "Stella Inabo",
            "display_name": "Stella Inabo",
            "team": "TJE58GTJL",
            "name": "stellainabo",
            "is_restricted": false,
            "is_ultra_restricted": false
        },
        "blocks": [
            {
                "type": "rich_text",
                "block_id": "nbI",
                "elements": [
                    {
                        "type": "rich_text_section",
                        "elements": [
                            {
                                "type": "text",
                                "text": "Hey "
                            },
                            {
                                "type": "user",
                                "user_id": "U0195CX543U"
                            },
                            {
                                "type": "text",
                                "text": " ! Nice to meet you"
                            },
                            {
                                "type": "emoji",
                                "name": "grin"
                            }
                        ]
                    }
                ]
            }
        ],
        "thread_ts": "1597888413.011100",
        "parent_user_id": "U0195CX543U"
    },
    {
        "client_msg_id": "4a6c87ca-f92d-486c-bb64-ba7a57f35931",
        "type": "message",
        "text": "Welcome <@U018YBQ05T7> :smiley:",
        "user": "U01704F04QH",
        "ts": "1598046651.051000",
        "team": "TJE58GTJL",
        "user_team": "TJE58GTJL",
        "source_team": "TJE58GTJL",
        "user_profile": {
            "avatar_hash": "c4babd35d9f8",
            "image_72": "https:\/\/avatars.slack-edge.com\/2020-09-04\/1343175645235_c4babd35d9f8360f26e8_72.jpg",
            "first_name": "Stella",
            "real_name": "Stella Inabo",
            "display_name": "Stella Inabo",
            "team": "TJE58GTJL",
            "name": "stellainabo",
            "is_restricted": false,
            "is_ultra_restricted": false
        },
        "blocks": [
            {
                "type": "rich_text",
                "block_id": "3JvAb",
                "elements": [
                    {
                        "type": "rich_text_section",
                        "elements": [
                            {
                                "type": "text",
                                "text": "Welcome "
                            },
                            {
                                "type": "user",
                                "user_id": "U018YBQ05T7"
                            },
                            {
                                "type": "text",
                                "text": " "
                            },
                            {
                                "type": "emoji",
                                "name": "smiley"
                            }
                        ]
                    }
                ]
            }
        ],
        "thread_ts": "1597720648.123100",
        "parent_user_id": "U018YBQ05T7",
        "reactions": [
            {
                "name": "heart",
                "users": [
                    "U018YBQ05T7"
                ],
                "count": 1
            }
        ]
    },
    {
        "client_msg_id": "b0d04171-a958-415c-97d3-597a8e63aa02",
        "type": "message",
        "text": "Hey <@U018YBRB03X>! Nice to meet you:smiley:",
        "user": "U01704F04QH",
        "ts": "1598046698.051300",
        "team": "TJE58GTJL",
        "user_team": "TJE58GTJL",
        "source_team": "TJE58GTJL",
        "user_profile": {
            "avatar_hash": "c4babd35d9f8",
            "image_72": "https:\/\/avatars.slack-edge.com\/2020-09-04\/1343175645235_c4babd35d9f8360f26e8_72.jpg",
            "first_name": "Stella",
            "real_name": "Stella Inabo",
            "display_name": "Stella Inabo",
            "team": "TJE58GTJL",
            "name": "stellainabo",
            "is_restricted": false,
            "is_ultra_restricted": false
        },
        "blocks": [
            {
                "type": "rich_text",
                "block_id": "J5CR",
                "elements": [
                    {
                        "type": "rich_text_section",
                        "elements": [
                            {
                                "type": "text",
                                "text": "Hey "
                            },
                            {
                                "type": "user",
                                "user_id": "U018YBRB03X"
                            },
                            {
                                "type": "text",
                                "text": "! Nice to meet you"
                            },
                            {
                                "type": "emoji",
                                "name": "smiley"
                            }
                        ]
                    }
                ]
            }
        ],
        "thread_ts": "1597721330.124800",
        "parent_user_id": "U018YBRB03X"
    },
    {
        "client_msg_id": "f0793417-450f-4398-822d-6e0a03d4ed3d",
        "type": "message",
        "text": "Welcome <@U0192P2G8F5> :smiley:",
        "user": "U01704F04QH",
        "ts": "1598046737.051600",
        "team": "TJE58GTJL",
        "user_team": "TJE58GTJL",
        "source_team": "TJE58GTJL",
        "user_profile": {
            "avatar_hash": "c4babd35d9f8",
            "image_72": "https:\/\/avatars.slack-edge.com\/2020-09-04\/1343175645235_c4babd35d9f8360f26e8_72.jpg",
            "first_name": "Stella",
            "real_name": "Stella Inabo",
            "display_name": "Stella Inabo",
            "team": "TJE58GTJL",
            "name": "stellainabo",
            "is_restricted": false,
            "is_ultra_restricted": false
        },
        "blocks": [
            {
                "type": "rich_text",
                "block_id": "INv",
                "elements": [
                    {
                        "type": "rich_text_section",
                        "elements": [
                            {
                                "type": "text",
                                "text": "Welcome "
                            },
                            {
                                "type": "user",
                                "user_id": "U0192P2G8F5"
                            },
                            {
                                "type": "text",
                                "text": " "
                            },
                            {
                                "type": "emoji",
                                "name": "smiley"
                            }
                        ]
                    }
                ]
            }
        ],
        "thread_ts": "1597784073.137300",
        "parent_user_id": "U0192P2G8F5"
    },
    {
        "client_msg_id": "75936e7f-44e1-4d0d-b71f-1fb21b4a679b",
        "type": "message",
        "text": "Welcome:wave:  <@U0192GZ406N>",
        "user": "U01704F04QH",
        "ts": "1598046788.051900",
        "team": "TJE58GTJL",
        "user_team": "TJE58GTJL",
        "source_team": "TJE58GTJL",
        "user_profile": {
            "avatar_hash": "c4babd35d9f8",
            "image_72": "https:\/\/avatars.slack-edge.com\/2020-09-04\/1343175645235_c4babd35d9f8360f26e8_72.jpg",
            "first_name": "Stella",
            "real_name": "Stella Inabo",
            "display_name": "Stella Inabo",
            "team": "TJE58GTJL",
            "name": "stellainabo",
            "is_restricted": false,
            "is_ultra_restricted": false
        },
        "blocks": [
            {
                "type": "rich_text",
                "block_id": "obh",
                "elements": [
                    {
                        "type": "rich_text_section",
                        "elements": [
                            {
                                "type": "text",
                                "text": "Welcome"
                            },
                            {
                                "type": "emoji",
                                "name": "wave"
                            },
                            {
                                "type": "text",
                                "text": "  "
                            },
                            {
                                "type": "user",
                                "user_id": "U0192GZ406N"
                            }
                        ]
                    }
                ]
            }
        ],
        "thread_ts": "1597854018.142900",
        "parent_user_id": "U0192GZ406N",
        "reactions": [
            {
                "name": "raised_hands",
                "users": [
                    "U0192GZ406N"
                ],
                "count": 1
            }
        ]
    },
    {
        "client_msg_id": "7802587d-c254-4250-a08f-f3e8fb40dee7",
        "type": "message",
        "text": "Welcome <@U018RV6JQR1> Nice to meet you:wave:",
        "user": "U01704F04QH",
        "ts": "1598046815.052200",
        "team": "TJE58GTJL",
        "user_team": "TJE58GTJL",
        "source_team": "TJE58GTJL",
        "user_profile": {
            "avatar_hash": "c4babd35d9f8",
            "image_72": "https:\/\/avatars.slack-edge.com\/2020-09-04\/1343175645235_c4babd35d9f8360f26e8_72.jpg",
            "first_name": "Stella",
            "real_name": "Stella Inabo",
            "display_name": "Stella Inabo",
            "team": "TJE58GTJL",
            "name": "stellainabo",
            "is_restricted": false,
            "is_ultra_restricted": false
        },
        "blocks": [
            {
                "type": "rich_text",
                "block_id": "jymj",
                "elements": [
                    {
                        "type": "rich_text_section",
                        "elements": [
                            {
                                "type": "text",
                                "text": "Welcome "
                            },
                            {
                                "type": "user",
                                "user_id": "U018RV6JQR1"
                            },
                            {
                                "type": "text",
                                "text": " Nice to meet you"
                            },
                            {
                                "type": "emoji",
                                "name": "wave"
                            }
                        ]
                    }
                ]
            }
        ],
        "thread_ts": "1597859149.148800",
        "parent_user_id": "U018RV6JQR1"
    },
    {
        "client_msg_id": "933EB088-E932-4F15-9EDF-3CF5F2AA4E0F",
        "type": "message",
        "text": "<@U01704F04QH>  thanks !",
        "user": "U018YBQ05T7",
        "ts": "1598047414.053000",
        "team": "TJE58GTJL",
        "user_team": "TJE58GTJL",
        "source_team": "TJE58GTJL",
        "user_profile": {
            "avatar_hash": "c85d66cc6562",
            "image_72": "https:\/\/avatars.slack-edge.com\/2020-08-17\/1299884473590_c85d66cc6562e6374774_72.png",
            "first_name": "Annette",
            "real_name": "Annette Aguirre",
            "display_name": "Annette",
            "team": "TJE58GTJL",
            "name": "annette.aguirre.7",
            "is_restricted": false,
            "is_ultra_restricted": false
        },
        "blocks": [
            {
                "type": "rich_text",
                "block_id": "9nL",
                "elements": [
                    {
                        "type": "rich_text_section",
                        "elements": [
                            {
                                "type": "user",
                                "user_id": "U01704F04QH"
                            },
                            {
                                "type": "text",
                                "text": "  thanks !"
                            }
                        ]
                    }
                ]
            }
        ],
        "thread_ts": "1597720648.123100",
        "parent_user_id": "U018YBQ05T7"
    },
    {
        "client_msg_id": "790bcf94-e896-41ee-a4e2-9dea579b81ca",
        "type": "message",
        "text": "Hey <@U01704F04QH>,nice to meet you!",
        "user": "U018YLTQJDU",
        "ts": "1598068977.053200",
        "team": "TJE58GTJL",
        "user_team": "TJE58GTJL",
        "source_team": "TJE58GTJL",
        "user_profile": {
            "avatar_hash": "9816e5481fd2",
            "image_72": "https:\/\/avatars.slack-edge.com\/2020-11-17\/1506465538819_9816e5481fd23b3da8b1_72.jpg",
            "first_name": "Ricks",
            "real_name": "Ricks N",
            "display_name": "Erick",
            "team": "TJE58GTJL",
            "name": "nyangenyaerick",
            "is_restricted": false,
            "is_ultra_restricted": false
        },
        "blocks": [
            {
                "type": "rich_text",
                "block_id": "MGKKf",
                "elements": [
                    {
                        "type": "rich_text_section",
                        "elements": [
                            {
                                "type": "text",
                                "text": "Hey "
                            },
                            {
                                "type": "user",
                                "user_id": "U01704F04QH"
                            },
                            {
                                "type": "text",
                                "text": ",nice to meet you!"
                            }
                        ]
                    }
                ]
            }
        ],
        "thread_ts": "1597909264.016400",
        "parent_user_id": "U018YLTQJDU"
    }
]