[
    {
        "client_msg_id": "584c8c52-c794-43f9-8c04-6c1dda50e0ce",
        "type": "message",
        "text": "I don't know if anyone has read this article (or how I stumbled across it), but it has some great ideas for content marketing, especially on effective ways to repurpose content. This is something I do a lot with my clients and it can make some big impacts on their rankings and messaging.\n\nHopefully y'all enjoy reading it as well!\n<https:\/\/kevintpayne.com\/content-marketing-ideas\/>",
        "user": "U030TFJMQ74",
        "ts": "1648048378.719649",
        "team": "TJE58GTJL",
        "user_team": "TJE58GTJL",
        "source_team": "TJE58GTJL",
        "user_profile": {
            "avatar_hash": "57abab855383",
            "image_72": "https:\/\/avatars.slack-edge.com\/2022-01-29\/3024742267221_57abab855383708e9560_72.jpg",
            "first_name": "Dylan",
            "real_name": "Dylan Miller",
            "display_name": "Dylan Miller",
            "team": "TJE58GTJL",
            "name": "dylan031",
            "is_restricted": false,
            "is_ultra_restricted": false
        },
        "blocks": [
            {
                "type": "rich_text",
                "block_id": "X7V",
                "elements": [
                    {
                        "type": "rich_text_section",
                        "elements": [
                            {
                                "type": "text",
                                "text": "I don't know if anyone has read this article (or how I stumbled across it), but it has some great ideas for content marketing, especially on effective ways to repurpose content. This is something I do a lot with my clients and it can make some big impacts on their rankings and messaging.\n\nHopefully y'all enjoy reading it as well!\n"
                            },
                            {
                                "type": "link",
                                "url": "https:\/\/kevintpayne.com\/content-marketing-ideas\/"
                            }
                        ]
                    }
                ]
            }
        ],
        "thread_ts": "1648048378.719649",
        "reply_count": 5,
        "reply_users_count": 3,
        "latest_reply": "1648123647.862399",
        "reply_users": [
            "U032Q4CT9G8",
            "U030TFJMQ74",
            "U035PRLFETU"
        ],
        "replies": [
            {
                "user": "U032Q4CT9G8",
                "ts": "1648049152.405519"
            },
            {
                "user": "U030TFJMQ74",
                "ts": "1648054066.613899"
            },
            {
                "user": "U035PRLFETU",
                "ts": "1648061649.158009"
            },
            {
                "user": "U030TFJMQ74",
                "ts": "1648123595.293969"
            },
            {
                "user": "U030TFJMQ74",
                "ts": "1648123647.862399"
            }
        ],
        "is_locked": false,
        "subscribed": false
    },
    {
        "client_msg_id": "98dd1a86-3e95-4da2-8c55-5a326a77bce5",
        "type": "message",
        "text": "I think the link is broken",
        "user": "U032Q4CT9G8",
        "ts": "1648049152.405519",
        "team": "TJE58GTJL",
        "user_team": "TJE58GTJL",
        "source_team": "TJE58GTJL",
        "user_profile": {
            "avatar_hash": "acda585807dd",
            "image_72": "https:\/\/avatars.slack-edge.com\/2022-02-07\/3081750552081_acda585807dd8ce5fbb1_72.jpg",
            "first_name": "Oluchukwu",
            "real_name": "Oluchukwu Njoku",
            "display_name": "Luu",
            "team": "TJE58GTJL",
            "name": "oluchukwunjoku1",
            "is_restricted": false,
            "is_ultra_restricted": false
        },
        "blocks": [
            {
                "type": "rich_text",
                "block_id": "wrU",
                "elements": [
                    {
                        "type": "rich_text_section",
                        "elements": [
                            {
                                "type": "text",
                                "text": "I think the link is broken"
                            }
                        ]
                    }
                ]
            }
        ],
        "thread_ts": "1648048378.719649",
        "parent_user_id": "U030TFJMQ74"
    },
    {
        "client_msg_id": "556c2cf8-1964-4fd8-a74c-c085dbe9fb0e",
        "type": "message",
        "text": "Oh yeah <@U032Q4CT9G8> - it looks like his blog is down? I was just reading it this morning and had the tab open...so I can still read it",
        "user": "U030TFJMQ74",
        "ts": "1648054066.613899",
        "team": "TJE58GTJL",
        "user_team": "TJE58GTJL",
        "source_team": "TJE58GTJL",
        "user_profile": {
            "avatar_hash": "57abab855383",
            "image_72": "https:\/\/avatars.slack-edge.com\/2022-01-29\/3024742267221_57abab855383708e9560_72.jpg",
            "first_name": "Dylan",
            "real_name": "Dylan Miller",
            "display_name": "Dylan Miller",
            "team": "TJE58GTJL",
            "name": "dylan031",
            "is_restricted": false,
            "is_ultra_restricted": false
        },
        "blocks": [
            {
                "type": "rich_text",
                "block_id": "m7b8r",
                "elements": [
                    {
                        "type": "rich_text_section",
                        "elements": [
                            {
                                "type": "text",
                                "text": "Oh yeah "
                            },
                            {
                                "type": "user",
                                "user_id": "U032Q4CT9G8"
                            },
                            {
                                "type": "text",
                                "text": " - it looks like his blog is down? I was just reading it this morning and had the tab open...so I can still read it"
                            }
                        ]
                    }
                ]
            }
        ],
        "thread_ts": "1648048378.719649",
        "parent_user_id": "U030TFJMQ74"
    },
    {
        "client_msg_id": "736abbed-f504-44c1-b062-bea4b6f9ac11",
        "type": "message",
        "text": "<@U032Q4CT9G8> and <@U030TFJMQ74> - Ross Simmonds is a master at sharing ways to repurpose content! Check him out: <https:\/\/www.google.com\/search?q=ross+simmonds+repurpose&amp;rlz=1C5CHFA_enCA934CA935&amp;oq=ross+simmonds+repurpose&amp;aqs=chrome..69i57j33i160.7352j0j4&amp;sourceid=chrome&amp;ie=UTF-8|https:\/\/www.google.com\/search?q=ross+simmonds+repurpose&amp;rlz=1C5CHFA_enCA934CA935&amp;oq=[…]se&amp;aqs=chrome..69i57j33i160.7352j0j4&amp;sourceid=chrome&amp;ie=UTF-8>",
        "user": "U035PRLFETU",
        "ts": "1648061649.158009",
        "team": "TJE58GTJL",
        "user_team": "TJE58GTJL",
        "source_team": "TJE58GTJL",
        "user_profile": {
            "avatar_hash": "41caeaf4d5c3",
            "image_72": "https:\/\/avatars.slack-edge.com\/2022-03-04\/3191157559541_41caeaf4d5c33193643c_72.jpg",
            "first_name": "Lily",
            "real_name": "Lily Lynch",
            "display_name": "Lily Lynch",
            "team": "TJE58GTJL",
            "name": "lily",
            "is_restricted": false,
            "is_ultra_restricted": false
        },
        "blocks": [
            {
                "type": "rich_text",
                "block_id": "SyY",
                "elements": [
                    {
                        "type": "rich_text_section",
                        "elements": [
                            {
                                "type": "user",
                                "user_id": "U032Q4CT9G8"
                            },
                            {
                                "type": "text",
                                "text": " and "
                            },
                            {
                                "type": "user",
                                "user_id": "U030TFJMQ74"
                            },
                            {
                                "type": "text",
                                "text": " - Ross Simmonds is a master at sharing ways to repurpose content! Check him out: "
                            },
                            {
                                "type": "link",
                                "url": "https:\/\/www.google.com\/search?q=ross+simmonds+repurpose&rlz=1C5CHFA_enCA934CA935&oq=ross+simmonds+repurpose&aqs=chrome..69i57j33i160.7352j0j4&sourceid=chrome&ie=UTF-8",
                                "text": "https:\/\/www.google.com\/search?q=ross+simmonds+repurpose&rlz=1C5CHFA_enCA934CA935&oq=[…]se&aqs=chrome..69i57j33i160.7352j0j4&sourceid=chrome&ie=UTF-8"
                            }
                        ]
                    }
                ]
            }
        ],
        "thread_ts": "1648048378.719649",
        "parent_user_id": "U030TFJMQ74",
        "reactions": [
            {
                "name": "+1",
                "users": [
                    "U032Q4CT9G8",
                    "U030TFJMQ74",
                    "U02CMV0AHAS"
                ],
                "count": 3
            }
        ]
    },
    {
        "client_msg_id": "8e01f4de-3abd-4de0-be79-2003f5a86d3f",
        "type": "message",
        "text": "I love the approach you're taking. Glassdoor does essentially the same thing, but gates their data in return for the reader's data. I wonder if you could do something like that?",
        "user": "U034FV9EJAC",
        "ts": "1648083590.593859",
        "team": "TJE58GTJL",
        "user_team": "TJE58GTJL",
        "source_team": "TJE58GTJL",
        "user_profile": {
            "avatar_hash": "a09b90619da6",
            "image_72": "https:\/\/avatars.slack-edge.com\/2022-02-24\/3179658752736_a09b90619da6d50b4845_72.jpg",
            "first_name": "Sarah",
            "real_name": "Sarah Guerrero",
            "display_name": "Sarah Guerrero",
            "team": "TJE58GTJL",
            "name": "sarah459",
            "is_restricted": false,
            "is_ultra_restricted": false
        },
        "edited": {
            "user": "U034FV9EJAC",
            "ts": "1648083601.000000"
        },
        "blocks": [
            {
                "type": "rich_text",
                "block_id": "qlSd",
                "elements": [
                    {
                        "type": "rich_text_section",
                        "elements": [
                            {
                                "type": "text",
                                "text": "I love the approach you're taking. Glassdoor does essentially the same thing, but gates their data in return for the reader's data. I wonder if you could do something like that?"
                            }
                        ]
                    }
                ]
            }
        ],
        "thread_ts": "1647384775.450399",
        "parent_user_id": "U0169509JG5",
        "reactions": [
            {
                "name": "ok_hand",
                "users": [
                    "U0169509JG5"
                ],
                "count": 1
            }
        ]
    }
]